{"packages":{"mhor\/php-mediainfo":{"1.0.0":{"name":"mhor\/php-mediainfo","description":"Simple class to parse mediainfo command","keywords":[],"homepage":"","version":"1.0.0","version_normalized":"1.0.0.0","license":["MIT"],"authors":[{"name":"mhor","email":"maxime.horcholle@gmail.com"}],"source":{"type":"git","url":"https:\/\/github.com\/mhor\/php-mediainfo.git","reference":"054814ccc90b39db93936e160064dec70cc28ebc"},"dist":{"type":"zip","url":"https:\/\/api.github.com\/repos\/mhor\/php-mediainfo\/zipball\/054814ccc90b39db93936e160064dec70cc28ebc","reference":"054814ccc90b39db93936e160064dec70cc28ebc","shasum":""},"type":"library","time":"2014-12-14T21:25:43+00:00","autoload":{"psr-4":{"Mhor\\MediaInfo\\":"src\/"}},"extra":{"branch-alias":{"dev-master":"v0.1.x-dev"}},"require":{"symfony\/process":"~2.3","symfony\/filesystem":"~2.3"},"require-dev":{"phpunit\/phpunit":"@stable","squizlabs\/php_codesniffer":"@stable","satooshi\/php-coveralls":"dev-master"},"uid":294752},"1.2.0":{"name":"mhor\/php-mediainfo","description":"Simple class to parse mediainfo command","keywords":[],"homepage":"","version":"1.2.0","version_normalized":"1.2.0.0","license":["MIT"],"authors":[{"name":"mhor","email":"maxime.horcholle@gmail.com"}],"source":{"type":"git","url":"https:\/\/github.com\/mhor\/php-mediainfo.git","reference":"5f4d6b0deff667713e64bef8891a71ad2b350a3a"},"dist":{"type":"zip","url":"https:\/\/api.github.com\/repos\/mhor\/php-mediainfo\/zipball\/5f4d6b0deff667713e64bef8891a71ad2b350a3a","reference":"5f4d6b0deff667713e64bef8891a71ad2b350a3a","shasum":""},"type":"library","time":"2015-01-25T10:52:10+00:00","autoload":{"psr-4":{"Mhor\\MediaInfo\\":"src\/"}},"extra":{"branch-alias":{"dev-master":"v1.1.x-dev"}},"require":{"symfony\/process":"~2.3","symfony\/filesystem":"~2.3"},"require-dev":{"phpunit\/phpunit":"@stable","squizlabs\/php_codesniffer":"@stable","satooshi\/php-coveralls":"dev-master"},"uid":313719},"1.2.1":{"name":"mhor\/php-mediainfo","description":"Simple class to parse mediainfo command","keywords":[],"homepage":"","version":"1.2.1","version_normalized":"1.2.1.0","license":["MIT"],"authors":[{"name":"mhor","email":"maxime.horcholle@gmail.com"}],"source":{"type":"git","url":"https:\/\/github.com\/mhor\/php-mediainfo.git","reference":"783833ddf09931044933fc53362de4a3a285af05"},"dist":{"type":"zip","url":"https:\/\/api.github.com\/repos\/mhor\/php-mediainfo\/zipball\/783833ddf09931044933fc53362de4a3a285af05","reference":"783833ddf09931044933fc53362de4a3a285af05","shasum":""},"type":"library","time":"2015-03-12T08:33:39+00:00","autoload":{"psr-4":{"Mhor\\MediaInfo\\":"src\/"}},"extra":{"branch-alias":{"dev-master":"v1.3.x-dev"}},"require":{"symfony\/process":"~2.3","symfony\/filesystem":"~2.3"},"require-dev":{"phpunit\/phpunit":"@stable","squizlabs\/php_codesniffer":"@stable","satooshi\/php-coveralls":"dev-master"},"uid":354285},"1.3.0":{"name":"mhor\/php-mediainfo","description":"Simple class to parse mediainfo command","keywords":[],"homepage":"","version":"1.3.0","version_normalized":"1.3.0.0","license":["MIT"],"authors":[{"name":"mhor","email":"maxime.horcholle@gmail.com"}],"source":{"type":"git","url":"https:\/\/github.com\/mhor\/php-mediainfo.git","reference":"ac3bc0730d50af945ac9a77003b7df615a7e218f"},"dist":{"type":"zip","url":"https:\/\/api.github.com\/repos\/mhor\/php-mediainfo\/zipball\/ac3bc0730d50af945ac9a77003b7df615a7e218f","reference":"ac3bc0730d50af945ac9a77003b7df615a7e218f","shasum":""},"type":"library","time":"2015-06-13T17:08:58+00:00","autoload":{"psr-4":{"Mhor\\MediaInfo\\":"src\/"}},"extra":{"branch-alias":{"dev-master":"v1.3.x-dev"}},"require":{"symfony\/process":"~2.3","symfony\/filesystem":"~2.3"},"require-dev":{"phpunit\/phpunit":"@stable","squizlabs\/php_codesniffer":"@stable","satooshi\/php-coveralls":"dev-master"},"uid":432801},"1.4.0":{"name":"mhor\/php-mediainfo","description":"Simple class to parse mediainfo command","keywords":[],"homepage":"","version":"1.4.0","version_normalized":"1.4.0.0","license":["MIT"],"authors":[{"name":"mhor","email":"maxime.horcholle@gmail.com"}],"source":{"type":"git","url":"https:\/\/github.com\/mhor\/php-mediainfo.git","reference":"fb8b88897f0c9e1186986682c04c10ba037c305a"},"dist":{"type":"zip","url":"https:\/\/api.github.com\/repos\/mhor\/php-mediainfo\/zipball\/fb8b88897f0c9e1186986682c04c10ba037c305a","reference":"fb8b88897f0c9e1186986682c04c10ba037c305a","shasum":""},"type":"library","time":"2015-06-14T18:56:57+00:00","autoload":{"psr-4":{"Mhor\\MediaInfo\\":"src\/"}},"extra":{"branch-alias":{"dev-master":"v2.0.x-dev"}},"require":{"symfony\/process":"~2.3","symfony\/filesystem":"~2.3"},"require-dev":{"phpunit\/phpunit":"@stable","squizlabs\/php_codesniffer":"@stable","satooshi\/php-coveralls":"dev-master"},"uid":433443},"1.4.1":{"name":"mhor\/php-mediainfo","description":"Simple class to parse mediainfo command","keywords":[],"homepage":"","version":"1.4.1","version_normalized":"1.4.1.0","license":["MIT"],"authors":[{"name":"mhor","email":"maxime.horcholle@gmail.com"}],"source":{"type":"git","url":"https:\/\/github.com\/mhor\/php-mediainfo.git","reference":"c3e51c7386b7fa4bd928b65ce37247577edd3dc0"},"dist":{"type":"zip","url":"https:\/\/api.github.com\/repos\/mhor\/php-mediainfo\/zipball\/c3e51c7386b7fa4bd928b65ce37247577edd3dc0","reference":"c3e51c7386b7fa4bd928b65ce37247577edd3dc0","shasum":""},"type":"library","time":"2015-06-14T20:26:41+00:00","autoload":{"psr-4":{"Mhor\\MediaInfo\\":"src\/"}},"extra":{"branch-alias":{"dev-master":"2.0.x-dev"}},"require":{"php":">=5.3.3","symfony\/process":"~2.3","symfony\/filesystem":"~2.3"},"require-dev":{"phpunit\/phpunit":"~4.0","squizlabs\/php_codesniffer":"~2.0","satooshi\/php-coveralls":"0.7.*@dev"},"uid":433468},"1.4.2":{"name":"mhor\/php-mediainfo","description":"PHP wrapper around the mediainfo command","keywords":[],"homepage":"","version":"1.4.2","version_normalized":"1.4.2.0","license":["MIT"],"authors":[{"name":"mhor","email":"maxime.horcholle@gmail.com"}],"source":{"type":"git","url":"https:\/\/github.com\/mhor\/php-mediainfo.git","reference":"ec78ce465e0e4e731e38dabeff733edc4df1d22f"},"dist":{"type":"zip","url":"https:\/\/api.github.com\/repos\/mhor\/php-mediainfo\/zipball\/ec78ce465e0e4e731e38dabeff733edc4df1d22f","reference":"ec78ce465e0e4e731e38dabeff733edc4df1d22f","shasum":""},"type":"library","time":"2015-07-08T20:47:23+00:00","autoload":{"psr-4":{"Mhor\\MediaInfo\\":"src\/"}},"extra":{"branch-alias":{"dev-master":"2.0.x-dev"}},"require":{"php":">=5.3.3","symfony\/process":"~2.3","symfony\/filesystem":"~2.3"},"require-dev":{"phpunit\/phpunit":"~4.0","squizlabs\/php_codesniffer":"~2.0","satooshi\/php-coveralls":"0.7.*@dev"},"uid":456368},"1.4.3":{"name":"mhor\/php-mediainfo","description":"PHP wrapper around the mediainfo command","keywords":[],"homepage":"","version":"1.4.3","version_normalized":"1.4.3.0","license":["MIT"],"authors":[{"name":"mhor","email":"maxime.horcholle@gmail.com"}],"source":{"type":"git","url":"https:\/\/github.com\/mhor\/php-mediainfo.git","reference":"6cba9f85ece08c213ec9a401944664b0b1f970bc"},"dist":{"type":"zip","url":"https:\/\/api.github.com\/repos\/mhor\/php-mediainfo\/zipball\/6cba9f85ece08c213ec9a401944664b0b1f970bc","reference":"6cba9f85ece08c213ec9a401944664b0b1f970bc","shasum":""},"type":"library","time":"2015-09-02T07:50:54+00:00","autoload":{"psr-4":{"Mhor\\MediaInfo\\":"src\/"}},"extra":{"branch-alias":{"dev-master":"2.0.x-dev"}},"require":{"php":">=5.3.3","symfony\/process":"~2.3","symfony\/filesystem":"~2.3"},"require-dev":{"phpunit\/phpunit":"~4.0","squizlabs\/php_codesniffer":"~2.0","satooshi\/php-coveralls":"0.7.*@dev"},"uid":509127},"1.4.4":{"name":"mhor\/php-mediainfo","description":"PHP wrapper around the mediainfo command","keywords":[],"homepage":"","version":"1.4.4","version_normalized":"1.4.4.0","license":["MIT"],"authors":[{"name":"mhor","email":"maxime.horcholle@gmail.com"}],"source":{"type":"git","url":"https:\/\/github.com\/mhor\/php-mediainfo.git","reference":"8c047a847dfac1b32ef855eb7326ce348d61a007"},"dist":{"type":"zip","url":"https:\/\/api.github.com\/repos\/mhor\/php-mediainfo\/zipball\/8c047a847dfac1b32ef855eb7326ce348d61a007","reference":"8c047a847dfac1b32ef855eb7326ce348d61a007","shasum":""},"type":"library","time":"2015-09-04T06:58:57+00:00","autoload":{"psr-4":{"Mhor\\MediaInfo\\":"src\/"}},"extra":{"branch-alias":{"dev-master":"2.0.x-dev"}},"require":{"php":">=5.3.3","symfony\/process":"~2.3","symfony\/filesystem":"~2.3"},"require-dev":{"phpunit\/phpunit":"~4.0","squizlabs\/php_codesniffer":"~2.0","satooshi\/php-coveralls":"0.7.*@dev"},"uid":511510},"1.5.0":{"name":"mhor\/php-mediainfo","description":"PHP wrapper around the mediainfo command","keywords":[],"homepage":"","version":"1.5.0","version_normalized":"1.5.0.0","license":["MIT"],"authors":[{"name":"mhor","email":"maxime.horcholle@gmail.com"}],"source":{"type":"git","url":"https:\/\/github.com\/mhor\/php-mediainfo.git","reference":"15bf1a1063128e4a5b051ef38634e0567a217401"},"dist":{"type":"zip","url":"https:\/\/api.github.com\/repos\/mhor\/php-mediainfo\/zipball\/15bf1a1063128e4a5b051ef38634e0567a217401","reference":"15bf1a1063128e4a5b051ef38634e0567a217401","shasum":""},"type":"library","time":"2015-09-16T20:53:49+00:00","autoload":{"psr-4":{"Mhor\\MediaInfo\\":"src\/"}},"extra":{"branch-alias":{"dev-master":"2.0.x-dev"}},"require":{"php":">=5.3.3","symfony\/process":"~2.3","symfony\/filesystem":"~2.3"},"require-dev":{"phpunit\/phpunit":"~4.0","squizlabs\/php_codesniffer":"~2.0","satooshi\/php-coveralls":"0.7.*@dev"},"uid":523849},"1.5.1":{"name":"mhor\/php-mediainfo","description":"PHP wrapper around the mediainfo command","keywords":[],"homepage":"","version":"1.5.1","version_normalized":"1.5.1.0","license":["MIT"],"authors":[{"name":"mhor","email":"maxime.horcholle@gmail.com"}],"source":{"type":"git","url":"https:\/\/github.com\/mhor\/php-mediainfo.git","reference":"7de07cb5312d00a145689d836bd0c9524cb65154"},"dist":{"type":"zip","url":"https:\/\/api.github.com\/repos\/mhor\/php-mediainfo\/zipball\/7de07cb5312d00a145689d836bd0c9524cb65154","reference":"7de07cb5312d00a145689d836bd0c9524cb65154","shasum":""},"type":"library","time":"2015-12-04T23:17:45+00:00","autoload":{"psr-4":{"Mhor\\MediaInfo\\":"src\/"}},"extra":{"branch-alias":{"dev-master":"2.0.x-dev"}},"require":{"php":">=5.3.3","symfony\/process":"~2.3|~3.0","symfony\/filesystem":"~2.3|~3.0"},"require-dev":{"phpunit\/phpunit":"~4.0","squizlabs\/php_codesniffer":"~2.0","satooshi\/php-coveralls":"0.7.*@dev"},"uid":609984},"1.5.2":{"name":"mhor\/php-mediainfo","description":"PHP wrapper around the mediainfo command","keywords":[],"homepage":"","version":"1.5.2","version_normalized":"1.5.2.0","license":["MIT"],"authors":[{"name":"mhor","email":"maxime.horcholle@gmail.com"}],"source":{"type":"git","url":"https:\/\/github.com\/mhor\/php-mediainfo.git","reference":"6ebd4f5ad3f0b62068e020aee8d99f7eee64a932"},"dist":{"type":"zip","url":"https:\/\/api.github.com\/repos\/mhor\/php-mediainfo\/zipball\/6ebd4f5ad3f0b62068e020aee8d99f7eee64a932","reference":"6ebd4f5ad3f0b62068e020aee8d99f7eee64a932","shasum":""},"type":"library","time":"2015-12-21T15:54:29+00:00","autoload":{"psr-4":{"Mhor\\MediaInfo\\":"src\/"}},"extra":{"branch-alias":{"dev-master":"2.0.x-dev"}},"require":{"php":">=5.3.3","symfony\/process":"~2.3|~3.0","symfony\/filesystem":"~2.3|~3.0"},"require-dev":{"phpunit\/phpunit":"~4.0","squizlabs\/php_codesniffer":"~2.0","satooshi\/php-coveralls":"0.7.*@dev"},"uid":629917},"1.5.3":{"name":"mhor\/php-mediainfo","description":"PHP wrapper around the mediainfo command","keywords":[],"homepage":"","version":"1.5.3","version_normalized":"1.5.3.0","license":["MIT"],"authors":[{"name":"mhor","email":"maxime.horcholle@gmail.com"}],"source":{"type":"git","url":"https:\/\/github.com\/mhor\/php-mediainfo.git","reference":"4eba89600f8c543925a3aaf879f50f1f40c96d28"},"dist":{"type":"zip","url":"https:\/\/api.github.com\/repos\/mhor\/php-mediainfo\/zipball\/4eba89600f8c543925a3aaf879f50f1f40c96d28","reference":"4eba89600f8c543925a3aaf879f50f1f40c96d28","shasum":""},"type":"library","time":"2015-12-21T17:11:31+00:00","autoload":{"psr-4":{"Mhor\\MediaInfo\\":"src\/"}},"extra":{"branch-alias":{"dev-master":"2.0.x-dev"}},"require":{"php":">=5.3.3","symfony\/process":"~2.3|~3.0","symfony\/filesystem":"~2.3|~3.0"},"require-dev":{"phpunit\/phpunit":"~4.0","squizlabs\/php_codesniffer":"~2.0","satooshi\/php-coveralls":"0.7.*@dev"},"uid":630010},"1.6.0":{"name":"mhor\/php-mediainfo","description":"PHP wrapper around the mediainfo command","keywords":[],"homepage":"","version":"1.6.0","version_normalized":"1.6.0.0","license":["MIT"],"authors":[{"name":"mhor","email":"maxime.horcholle@gmail.com"}],"source":{"type":"git","url":"https:\/\/github.com\/mhor\/php-mediainfo.git","reference":"7edba90ffd500ab3744a48ace6e0e517151182e6"},"dist":{"type":"zip","url":"https:\/\/api.github.com\/repos\/mhor\/php-mediainfo\/zipball\/7edba90ffd500ab3744a48ace6e0e517151182e6","reference":"7edba90ffd500ab3744a48ace6e0e517151182e6","shasum":""},"type":"library","time":"2016-01-24T13:22:25+00:00","autoload":{"psr-4":{"Mhor\\MediaInfo\\":"src\/"}},"extra":{"branch-alias":{"dev-master":"2.0.x-dev"}},"require":{"php":">=5.3.3","symfony\/process":"~2.3|~3.0","symfony\/filesystem":"~2.3|~3.0"},"require-dev":{"phpunit\/phpunit":"~4.0","squizlabs\/php_codesniffer":"~2.0","satooshi\/php-coveralls":"0.7.*@dev"},"uid":670098},"2.0.0":{"name":"mhor\/php-mediainfo","description":"PHP wrapper around the mediainfo command","keywords":[],"homepage":"","version":"2.0.0","version_normalized":"2.0.0.0","license":["MIT"],"authors":[{"name":"mhor","email":"maxime.horcholle@gmail.com"}],"source":{"type":"git","url":"https:\/\/github.com\/mhor\/php-mediainfo.git","reference":"37e4e1a88b7812468fb09fa553dfa90e3d64a06a"},"dist":{"type":"zip","url":"https:\/\/api.github.com\/repos\/mhor\/php-mediainfo\/zipball\/37e4e1a88b7812468fb09fa553dfa90e3d64a06a","reference":"37e4e1a88b7812468fb09fa553dfa90e3d64a06a","shasum":""},"type":"library","time":"2016-05-02T20:49:25+00:00","autoload":{"psr-4":{"Mhor\\MediaInfo\\":"src\/"}},"extra":{"branch-alias":{"dev-master":"3.0.x-dev"}},"require":{"php":">=5.4.0","symfony\/process":"~2.3|~3.0","symfony\/filesystem":"~2.3|~3.0"},"require-dev":{"phpunit\/phpunit":"~4.0","squizlabs\/php_codesniffer":"~2.0","satooshi\/php-coveralls":"0.7.*@dev"},"uid":804034},"2.1.0":{"name":"mhor\/php-mediainfo","description":"PHP wrapper around the mediainfo command","keywords":[],"homepage":"","version":"2.1.0","version_normalized":"2.1.0.0","license":["MIT"],"authors":[{"name":"mhor","email":"maxime.horcholle@gmail.com"}],"source":{"type":"git","url":"https:\/\/github.com\/mhor\/php-mediainfo.git","reference":"b4f9b9c6fd2c7178eeced971bd1d6760b404ccca"},"dist":{"type":"zip","url":"https:\/\/api.github.com\/repos\/mhor\/php-mediainfo\/zipball\/b4f9b9c6fd2c7178eeced971bd1d6760b404ccca","reference":"b4f9b9c6fd2c7178eeced971bd1d6760b404ccca","shasum":""},"type":"library","time":"2016-05-06T07:22:41+00:00","autoload":{"psr-4":{"Mhor\\MediaInfo\\":"src\/"}},"extra":{"branch-alias":{"dev-master":"3.0.x-dev"}},"require":{"php":">=5.4.0","symfony\/process":"~2.3|~3.0","symfony\/filesystem":"~2.3|~3.0"},"require-dev":{"phpunit\/phpunit":"~4.0","squizlabs\/php_codesniffer":"~2.0","satooshi\/php-coveralls":"0.7.*@dev"},"uid":808887},"2.2.0":{"name":"mhor\/php-mediainfo","description":"PHP wrapper around the mediainfo command","keywords":[],"homepage":"","version":"2.2.0","version_normalized":"2.2.0.0","license":["MIT"],"authors":[{"name":"mhor","email":"maxime.horcholle@gmail.com"}],"source":{"type":"git","url":"https:\/\/github.com\/mhor\/php-mediainfo.git","reference":"d39ab01046cd3bb355468e1f87c0a0cee6ccaf80"},"dist":{"type":"zip","url":"https:\/\/api.github.com\/repos\/mhor\/php-mediainfo\/zipball\/d39ab01046cd3bb355468e1f87c0a0cee6ccaf80","reference":"d39ab01046cd3bb355468e1f87c0a0cee6ccaf80","shasum":""},"type":"library","time":"2016-05-22T11:16:17+00:00","autoload":{"psr-4":{"Mhor\\MediaInfo\\":"src\/"}},"extra":{"branch-alias":{"dev-master":"3.0.x-dev"}},"require":{"php":">=5.4.0","symfony\/process":"~2.3|~3.0","symfony\/filesystem":"~2.3|~3.0"},"require-dev":{"phpunit\/phpunit":"~4.0"},"uid":831790},"2.2.1":{"name":"mhor\/php-mediainfo","description":"PHP wrapper around the mediainfo command","keywords":[],"homepage":"","version":"2.2.1","version_normalized":"2.2.1.0","license":["MIT"],"authors":[{"name":"mhor","email":"maxime.horcholle@gmail.com"}],"source":{"type":"git","url":"https:\/\/github.com\/mhor\/php-mediainfo.git","reference":"98ff1dc243332d2b3f41489fd8301c0a622d8da2"},"dist":{"type":"zip","url":"https:\/\/api.github.com\/repos\/mhor\/php-mediainfo\/zipball\/98ff1dc243332d2b3f41489fd8301c0a622d8da2","reference":"98ff1dc243332d2b3f41489fd8301c0a622d8da2","shasum":""},"type":"library","time":"2016-07-11T09:19:31+00:00","autoload":{"psr-4":{"Mhor\\MediaInfo\\":"src\/"}},"extra":{"branch-alias":{"dev-master":"3.0.x-dev"}},"require":{"php":">=5.4.0","symfony\/process":"~2.3|~3.0","symfony\/filesystem":"~2.3|~3.0"},"require-dev":{"phpunit\/phpunit":"~4.0"},"uid":896994},"2.2.2":{"name":"mhor\/php-mediainfo","description":"PHP wrapper around the mediainfo command","keywords":[],"homepage":"","version":"2.2.2","version_normalized":"2.2.2.0","license":["MIT"],"authors":[{"name":"mhor","email":"maxime.horcholle@gmail.com"}],"source":{"type":"git","url":"https:\/\/github.com\/mhor\/php-mediainfo.git","reference":"4f8f9534213f558d4bdfcc7177d665d4542a7550"},"dist":{"type":"zip","url":"https:\/\/api.github.com\/repos\/mhor\/php-mediainfo\/zipball\/4f8f9534213f558d4bdfcc7177d665d4542a7550","reference":"4f8f9534213f558d4bdfcc7177d665d4542a7550","shasum":""},"type":"library","time":"2016-09-04T09:35:12+00:00","autoload":{"psr-4":{"Mhor\\MediaInfo\\":"src\/"}},"extra":{"branch-alias":{"dev-master":"3.0.x-dev"}},"require":{"php":">=5.4.0","symfony\/process":"~2.3|~3.0","symfony\/filesystem":"~2.3|~3.0"},"require-dev":{"phpunit\/phpunit":"~4.0"},"uid":978271},"2.3.0":{"name":"mhor\/php-mediainfo","description":"PHP wrapper around the mediainfo command","keywords":[],"homepage":"","version":"2.3.0","version_normalized":"2.3.0.0","license":["MIT"],"authors":[{"name":"mhor","email":"maxime.horcholle@gmail.com"}],"source":{"type":"git","url":"https:\/\/github.com\/mhor\/php-mediainfo.git","reference":"25273284c993e4bc067e7d00232b07897a0c707f"},"dist":{"type":"zip","url":"https:\/\/api.github.com\/repos\/mhor\/php-mediainfo\/zipball\/25273284c993e4bc067e7d00232b07897a0c707f","reference":"25273284c993e4bc067e7d00232b07897a0c707f","shasum":""},"type":"library","time":"2017-01-13T20:01:19+00:00","autoload":{"psr-4":{"Mhor\\MediaInfo\\":"src\/"}},"extra":{"branch-alias":{"dev-master":"3.0.x-dev"}},"require":{"php":">=5.4.0","symfony\/process":"~2.3|~3.0","symfony\/filesystem":"~2.3|~3.0"},"require-dev":{"phpunit\/phpunit":"~4.0"},"uid":1172124},"2.3.1":{"name":"mhor\/php-mediainfo","description":"PHP wrapper around the mediainfo command","keywords":[],"homepage":"","version":"2.3.1","version_normalized":"2.3.1.0","license":["MIT"],"authors":[{"name":"mhor","email":"maxime.horcholle@gmail.com"}],"source":{"type":"git","url":"https:\/\/github.com\/mhor\/php-mediainfo.git","reference":"53961b37c0521c1b067de91c8ff24da3474592a0"},"dist":{"type":"zip","url":"https:\/\/api.github.com\/repos\/mhor\/php-mediainfo\/zipball\/53961b37c0521c1b067de91c8ff24da3474592a0","reference":"53961b37c0521c1b067de91c8ff24da3474592a0","shasum":""},"type":"library","time":"2017-01-15T21:31:32+00:00","autoload":{"psr-4":{"Mhor\\MediaInfo\\":"src\/"}},"extra":{"branch-alias":{"dev-master":"3.0.x-dev"}},"require":{"php":">=5.4.0","symfony\/process":"~2.3|~3.0","symfony\/filesystem":"~2.3|~3.0"},"require-dev":{"phpunit\/phpunit":"~4.0"},"uid":1174348},"3.0.0":{"name":"mhor\/php-mediainfo","description":"PHP wrapper around the mediainfo command","keywords":[],"homepage":"","version":"3.0.0","version_normalized":"3.0.0.0","license":["MIT"],"authors":[{"name":"mhor","email":"maxime.horcholle@gmail.com"}],"source":{"type":"git","url":"https:\/\/github.com\/mhor\/php-mediainfo.git","reference":"a16bad2b884dc17d40fcea432115ec0c3ec0e739"},"dist":{"type":"zip","url":"https:\/\/api.github.com\/repos\/mhor\/php-mediainfo\/zipball\/a16bad2b884dc17d40fcea432115ec0c3ec0e739","reference":"a16bad2b884dc17d40fcea432115ec0c3ec0e739","shasum":""},"type":"library","time":"2017-01-17T22:45:20+00:00","autoload":{"psr-4":{"Mhor\\MediaInfo\\":"src\/"}},"extra":{"branch-alias":{"dev-master":"4.0.x-dev"}},"require":{"php":">=5.4.0","symfony\/process":"~2.3|~3.0","symfony\/filesystem":"~2.3|~3.0"},"require-dev":{"phpunit\/phpunit":"~4.0"},"uid":1178642},"dev-master":{"name":"mhor\/php-mediainfo","description":"PHP wrapper around the mediainfo command","keywords":[],"homepage":"","version":"dev-master","version_normalized":"9999999-dev","license":["MIT"],"authors":[{"name":"mhor","email":"maxime.horcholle@gmail.com"}],"source":{"type":"git","url":"https:\/\/github.com\/mhor\/php-mediainfo.git","reference":"a5be8881b1d7f6d957803818a281cb1fc25a5a71"},"dist":{"type":"zip","url":"https:\/\/api.github.com\/repos\/mhor\/php-mediainfo\/zipball\/a5be8881b1d7f6d957803818a281cb1fc25a5a71","reference":"a5be8881b1d7f6d957803818a281cb1fc25a5a71","shasum":""},"type":"library","time":"2017-05-30T15:59:13+00:00","autoload":{"psr-4":{"Mhor\\MediaInfo\\":"src\/"}},"extra":{"branch-alias":{"dev-master":"4.0.x-dev"}},"require":{"symfony\/process":"~2.3|~3.0","symfony\/filesystem":"~2.3|~3.0","php":">=5.4.0"},"require-dev":{"phpunit\/phpunit":"~4.0"},"uid":286904}}}}